shiftml/__init__.py
shiftml/ase/__init__.py
shiftml/ase/calculator.py
shiftml/utils/tensorial.py
shiftml-0.1.0.dist-info/licenses/LICENSE
shiftml-0.1.0.dist-info/METADATA
shiftml-0.1.0.dist-info/WHEEL
shiftml-0.1.0.dist-info/top_level.txt
shiftml-0.1.0.dist-info/RECORD
