Metadata-Version: 2.4
Name: shiftml
Version: 0.1.0
Summary: Predictions of chemical shieldings using machine learning
License: BSD-3-Clause
Project-URL: homepage, https://github.com/lab-cosmo/ShiftML
Project-URL: repository, https://github.com/lab-cosmo/ShiftML
Requires-Python: >=3.9
License-File: LICENSE
Requires-Dist: ase
Requires-Dist: platformdirs
Requires-Dist: metatensor-learn==0.3.1
Requires-Dist: metatensor-operations==0.3.1
Requires-Dist: metatensor-torch==0.7.3
Requires-Dist: vesin
Dynamic: license-file
